pymoebot/__about__.py
pymoebot/__init__.py
test/__init__.py
test/model_test.py
pymoebot-0.3.1.dist-info/METADATA
pymoebot-0.3.1.dist-info/WHEEL
pymoebot-0.3.1.dist-info/top_level.txt
pymoebot-0.3.1.dist-info/RECORD
