Metadata-Version: 2.1
Name: pymoebot
Version: 0.3.1
Summary: A Python library intended to monitor and control MoeBot robotic lawn mowers.
Home-page: https://github.com/Whytey/pymoebot
Author: David Whyte
Author-email: David@Whyte.xyz
Classifier: Programming Language :: Python :: 3
Classifier: Operating System :: OS Independent
Requires-Dist: tinytuya
